LICENSE
MANIFEST.in
README.md
requirements.txt
setup.py
bin/skewer
skewer/__init__.py
skewer/_version
skewer/skewer-es-template.json
skewer.egg-info/PKG-INFO
skewer.egg-info/SOURCES.txt
skewer.egg-info/dependency_links.txt
skewer.egg-info/requires.txt
skewer.egg-info/top_level.txt