Metadata-Version: 1.1
Name: skewer
Version: 0.1
Summary: Enumerate AWS resources and index them in ElasticSearch
Home-page: https://github.com/scopely-devops/skewer
Author: Mitch Garnaat
Author-email: mitch@scopely.com
License: Apache License
